k3s_status_lcd/__init__.py
k3s_status_lcd/status.py
k3s_status_lcd-0.1.1.dist-info/WHEEL
k3s_status_lcd-0.1.1.dist-info/METADATA
k3s_status_lcd-0.1.1.dist-info/RECORD
